AgenticLearnPro/__init__.py
AgenticLearnPro/agent.py
AgenticLearnPro/environment.py
agenticlearnpro-0.1.2.dist-info/licenses/LICENSE
agenticlearnpro-0.1.2.dist-info/METADATA
agenticlearnpro-0.1.2.dist-info/WHEEL
agenticlearnpro-0.1.2.dist-info/top_level.txt
agenticlearnpro-0.1.2.dist-info/RECORD
