Metadata-Version: 2.4
Name: AgenticLearnPro
Version: 0.1.2
Summary: A simple agentic AI package using reinforcement learning
Home-page: https://github.com/stephanieewelu/AgenticLearnPro
Author: Stephanie Ewelu
Author-email: stephanieewelu@gmail.com
Classifier: Programming Language :: Python :: 3
Classifier: License :: OSI Approved :: MIT License
Classifier: Operating System :: OS Independent
Requires-Python: >=3.6
License-File: LICENSE
Requires-Dist: numpy>=1.19
Requires-Dist: gymnasium>=0.29
Dynamic: author
Dynamic: author-email
Dynamic: classifier
Dynamic: description
Dynamic: description-content-type
Dynamic: home-page
Dynamic: license-file
Dynamic: requires-dist
Dynamic: requires-python
Dynamic: summary
